decimaltodoubleword.py
decimaltodoubleword-1.0.0.dist-info/LICENSE
decimaltodoubleword-1.0.0.dist-info/WHEEL
decimaltodoubleword-1.0.0.dist-info/METADATA
decimaltodoubleword-1.0.0.dist-info/RECORD
