Metadata-Version: 2.1
Name: decimaltodoubleword
Version: 1.0.0
Summary: Function to convert a decimal integer to four byte doubleword
Home-page: https://github.com/saschahoeche
License: UNKNOWN
Author: Sascha Hoeche
Author-email: sascha.hoeche@gmx.com
Classifier: License :: OSI Approved :: GNU General Public License v3 or later (GPLv3+)
